django_premailer/__init__.py
django_premailer/models.py
django_premailer/templatetags/__init__.py
django_premailer/templatetags/premailer.py
django_premailer/tests/__init__.py
django_premailer/tests/settings.py
django_premailer/tests/test_templatetags.py
django_premailer/tests/templates/basic-base-url.expected.html
django_premailer/tests/templates/basic-base-url.html
django_premailer/tests/templates/basic.expected.html
django_premailer/tests/templates/basic.html
django_premailer-0.2.0.dist-info/DESCRIPTION.rst
django_premailer-0.2.0.dist-info/METADATA
django_premailer-0.2.0.dist-info/RECORD
django_premailer-0.2.0.dist-info/WHEEL
django_premailer-0.2.0.dist-info/metadata.json
django_premailer-0.2.0.dist-info/top_level.txt
